pakj/__init__.py
pakj/hello.py
pakj-0.0.1.dist-info/METADATA
pakj-0.0.1.dist-info/WHEEL
pakj-0.0.1.dist-info/RECORD
